hfurl/__init__.py
hfurl-0.2.0.dist-info/LICENSE
hfurl-0.2.0.dist-info/WHEEL
hfurl-0.2.0.dist-info/METADATA
hfurl-0.2.0.dist-info/RECORD
