Metadata-Version: 2.1
Name: hfurl
Version: 0.2.0
Summary: Human-friendly URL parsing in python
Home-page: https://github.com/cmd410/hfurl
License: LGPL-2.1-only
Keywords: url,parse
Author: Crystal Melting Dot
Author-email: stresspassing@gmail.com
Requires-Python: >=3.8,<4.0
Classifier: License :: OSI Approved
Classifier: Programming Language :: Python :: 3
Classifier: Programming Language :: Python :: 3.10
Classifier: Programming Language :: Python :: 3.8
Classifier: Programming Language :: Python :: 3.9
Project-URL: Repository, https://github.com/cmd410/hfurl
